highlight_ranges/__init__.py
highlight_ranges/filters.py
highlight_ranges/styles.py
highlight_ranges/version.py
pygments_ranges/__init__.py
pygments_ranges/lexer.py
pygments_ranges/version.py
highlight_ranges-1.0.0.dist-info/LICENSE
highlight_ranges-1.0.0.dist-info/METADATA
highlight_ranges-1.0.0.dist-info/WHEEL
highlight_ranges-1.0.0.dist-info/entry_points.txt
highlight_ranges-1.0.0.dist-info/top_level.txt
highlight_ranges-1.0.0.dist-info/RECORD
