Metadata-Version: 2.1
Name: highlight-ranges
Version: 1.0.0
Summary: Highlighting ranges in pygments
Home-page: http://github.com/sixty-north/highlight-ranges/
Author: Sixty North AS
Author-email: austin@sixty-north.com
License: MIT
Platform: any
Classifier: Development Status :: 3 - Alpha
Classifier: Operating System :: OS Independent
Classifier: Programming Language :: Python
Classifier: Programming Language :: Python :: 3 :: Only
Requires-Dist: pygments
Requires-Dist: spor
Provides-Extra: dev
Requires-Dist: black ; extra == 'dev'
Requires-Dist: flake8 ; extra == 'dev'
Requires-Dist: twine ; extra == 'dev'
Requires-Dist: wheel ; extra == 'dev'
Provides-Extra: test
Requires-Dist: pytest ; extra == 'test'
